MANIFEST.in
README.rst
pyvenv.cfg
setup.py
docs/CREDITS.txt
docs/HISTORY.rst
docs/LICENSE.txt
src/roughrider/__init__.py
src/roughrider.application.egg-info/PKG-INFO
src/roughrider.application.egg-info/SOURCES.txt
src/roughrider.application.egg-info/dependency_links.txt
src/roughrider.application.egg-info/namespace_packages.txt
src/roughrider.application.egg-info/not-zip-safe
src/roughrider.application.egg-info/requires.txt
src/roughrider.application.egg-info/top_level.txt
src/roughrider/application/__init__.py
src/roughrider/application/middleware.py
src/roughrider/application/request.py
tests/test_application.py
tests/test_middlewares.py
tests/test_request.py