Metadata-Version: 2.1
Name: roughrider.application
Version: 0.2
Summary: Run-of-the-mill WSGI application base with URL routing.
Home-page: https://github.com/HorsemanWSGI/roughrider.application
Author: Souheil CHELFOUH
Author-email: trollfot@gmail.com
License: ZPL
Download-URL: http://pypi.python.org/pypi/roughrider.application
Platform: UNKNOWN
Classifier: Environment :: Web Environment
Classifier: Intended Audience :: Developers
Classifier: License :: OSI Approved :: Zope Public License
Classifier: Programming Language :: Python :: 3.8
Classifier: Programming Language :: Python :: 3.9
Classifier: Programming Language :: Python :: 3.10
Classifier: Topic :: Internet :: WWW/HTTP :: WSGI
Provides-Extra: test
